flyhiawa_math-0.0.6.dist-info/licenses/LICENSE.md
flyhiawalib/Arithmetic.py
flyhiawalib/Physical.py
flyhiawalib/__init__.py
flyhiawalib/Geometry/Basic.py
flyhiawalib/Geometry/Multidimensions.py
flyhiawalib/Geometry/__init__.py
flyhiawalib/Statistics/__init__.py
flyhiawalib/Statistics/means.py
flyhiawa_math-0.0.6.dist-info/METADATA
flyhiawa_math-0.0.6.dist-info/WHEEL
flyhiawa_math-0.0.6.dist-info/top_level.txt
flyhiawa_math-0.0.6.dist-info/RECORD
