Metadata-Version: 2.4
Name: flyhiawa-math
Version: 0.0.6
Summary: Uma biblioteca de matemática com várias fórmulas!
Author-email: Flyhiawa <flyhiawa@email.com>
License: MIT
Requires-Python: >=3.10
License-File: LICENSE.md
Dynamic: license-file
